[{"Health_Camp_ID": 6560, "Camp_Start_Date": "16-Aug-03", "Camp_End_Date": "20-Aug-03", "Category1": "First", "Category2": "B", "Category3": "2"}, {"Health_Camp_ID": 6530, "Camp_Start_Date": "16-Aug-03", "Camp_End_Date": "28-Oct-03", "Category1": "First", "Category2": "C", "Category3": "2"}, {"Health_Camp_ID": 6544, "Camp_Start_Date": "03-Nov-03", "Camp_End_Date": "15-Nov-03", "Category1": "First", "Category2": "F", "Category3": "1"}, {"Health_Camp_ID": 6585, "Camp_Start_Date": "22-Nov-03", "Camp_End_Date": "05-Dec-03", "Category1": "First", "Category2": "E", "Category3": "2"}, {"Health_Camp_ID": 6561, "Camp_Start_Date": "30-Nov-03", "Camp_End_Date": "18-Dec-03", "Category1": "First", "Category2": "E", "Category3": "1"}, {"Health_Camp_ID": 6581, "Camp_Start_Date": "07-Dec-03", "Camp_End_Date": "13-Jun-04", "Category1": "First", "Category2": "F", "Category3": "2"}, {"Health_Camp_ID": 6564, "Camp_Start_Date": "17-Dec-03", "Camp_End_Date": "11-Jun-04", "Category1": "First", "Category2": "C", "Category3": "2"}, {"Health_Camp_ID": 6557, "Camp_Start_Date": "04-Jan-04", "Camp_End_Date": "09-Jan-04", "Category1": "First", "Category2": "C", "Category3": "2"}, {"Health_Camp_ID": 6538, "Camp_Start_Date": "09-Jan-04", "Camp_End_Date": "04-Feb-05", "Category1": "First", "Category2": "F", "Category3": "2"}, {"Health_Camp_ID": 6546, "Camp_Start_Date": "09-Jan-04", "Camp_End_Date": "17-Jan-04", "Category1": "First", "Category2": "E", "Category3": "2"}, {"Health_Camp_ID": 6535, "Camp_Start_Date": "01-Feb-04", "Camp_End_Date": "18-Feb-04", "Category1": "First", "Category2": "E", "Category3": "2"}, {"Health_Camp_ID": 6553, "Camp_Start_Date": "26-Apr-04", "Camp_End_Date": "04-May-04", "Category1": "First", "Category2": "C", "Category3": "2"}, {"Health_Camp_ID": 6565, "Camp_Start_Date": "29-Apr-04", "Camp_End_Date": "04-May-04", "Category1": "First", "Category2": "C", "Category3": "2"}, {"Health_Camp_ID": 6552, "Camp_Start_Date": "21-May-04", "Camp_End_Date": "24-May-04", "Category1": "First", "Category2": "C", "Category3": "2"}, {"Health_Camp_ID": 6539, "Camp_Start_Date": "07-Aug-04", "Camp_End_Date": "12-Feb-05", "Category1": "First", "Category2": "F", "Category3": "2"}, {"Health_Camp_ID": 6558, "Camp_Start_Date": "22-Aug-04", "Camp_End_Date": "27-Aug-04", "Category1": "First", "Category2": "C", "Category3": "2"}, {"Health_Camp_ID": 6563, "Camp_Start_Date": "09-Sep-04", "Camp_End_Date": "14-Sep-04", "Category1": "First", "Category2": "C", "Category3": "2"}, {"Health_Camp_ID": 6569, "Camp_Start_Date": "17-Sep-04", "Camp_End_Date": "20-Sep-04", "Category1": "First", "Category2": "C", "Category3": "2"}, {"Health_Camp_ID": 6586, "Camp_Start_Date": "01-Oct-04", "Camp_End_Date": "18-Oct-04", "Category1": "First", "Category2": "E", "Category3": "2"}, {"Health_Camp_ID": 6540, "Camp_Start_Date": "01-Nov-04", "Camp_End_Date": "04-Nov-04", "Category1": "First", "Category2": "E", "Category3": "2"}, {"Health_Camp_ID": 6562, "Camp_Start_Date": "24-Nov-04", "Camp_End_Date": "02-Jun-05", "Category1": "First", "Category2": "F", "Category3": "2"}, {"Health_Camp_ID": 6531, "Camp_Start_Date": "09-Dec-04", "Camp_End_Date": "14-Dec-04", "Category1": "First", "Category2": "C", "Category3": "2"}, {"Health_Camp_ID": 6580, "Camp_Start_Date": "22-Dec-04", "Camp_End_Date": "06-Jan-05", "Category1": "First", "Category2": "E", "Category3": "2"}, {"Health_Camp_ID": 6526, "Camp_Start_Date": "03-Jan-05", "Camp_End_Date": "20-Feb-05", "Category1": "First", "Category2": "E", "Category3": "2"}, {"Health_Camp_ID": 6536, "Camp_Start_Date": "15-Feb-05", "Camp_End_Date": "18-Feb-05", "Category1": "Second", "Category2": "D", "Category3": "2"}, {"Health_Camp_ID": 6542, "Camp_Start_Date": "19-Feb-05", "Camp_End_Date": "23-Aug-05", "Category1": "First", "Category2": "F", "Category3": "2"}, {"Health_Camp_ID": 6532, "Camp_Start_Date": "19-Feb-05", "Camp_End_Date": "23-Aug-05", "Category1": "First", "Category2": "F", "Category3": "2"}, {"Health_Camp_ID": 6523, "Camp_Start_Date": "23-Feb-05", "Camp_End_Date": "16-Sep-05", "Category1": "Second", "Category2": "D", "Category3": "2"}, {"Health_Camp_ID": 6524, "Camp_Start_Date": "13-May-05", "Camp_End_Date": "21-May-05", "Category1": "First", "Category2": "C", "Category3": "2"}, {"Health_Camp_ID": 6527, "Camp_Start_Date": "13-Jun-05", "Camp_End_Date": "22-Jul-05", "Category1": "Third", "Category2": "G", "Category3": "2"}, {"Health_Camp_ID": 6554, "Camp_Start_Date": "19-Jun-05", "Camp_End_Date": "01-Jul-05", "Category1": "First", "Category2": "B", "Category3": "2"}, {"Health_Camp_ID": 6549, "Camp_Start_Date": "23-Jun-05", "Camp_End_Date": "27-Jun-05", "Category1": "Second", "Category2": "A", "Category3": "2"}, {"Health_Camp_ID": 6570, "Camp_Start_Date": "09-Jul-05", "Camp_End_Date": "22-Jul-05", "Category1": "First", "Category2": "E", "Category3": "2"}, {"Health_Camp_ID": 6587, "Camp_Start_Date": "02-Aug-05", "Camp_End_Date": "09-Aug-05", "Category1": "First", "Category2": "E", "Category3": "1"}, {"Health_Camp_ID": 6578, "Camp_Start_Date": "16-Aug-05", "Camp_End_Date": "14-Oct-05", "Category1": "Third", "Category2": "G", "Category3": "2"}, {"Health_Camp_ID": 6555, "Camp_Start_Date": "15-Sep-05", "Camp_End_Date": "19-Sep-05", "Category1": "Second", "Category2": "A", "Category3": "2"}, {"Health_Camp_ID": 6543, "Camp_Start_Date": "27-Sep-05", "Camp_End_Date": "07-Nov-07", "Category1": "First", "Category2": "F", "Category3": "2"}, {"Health_Camp_ID": 6537, "Camp_Start_Date": "27-Sep-05", "Camp_End_Date": "07-Nov-07", "Category1": "First", "Category2": "F", "Category3": "2"}, {"Health_Camp_ID": 6571, "Camp_Start_Date": "09-Oct-05", "Camp_End_Date": "12-Oct-05", "Category1": "First", "Category2": "E", "Category3": "2"}, {"Health_Camp_ID": 6575, "Camp_Start_Date": "12-Oct-05", "Camp_End_Date": "14-Oct-05", "Category1": "First", "Category2": "C", "Category3": "2"}, {"Health_Camp_ID": 6534, "Camp_Start_Date": "17-Oct-05", "Camp_End_Date": "07-Nov-07", "Category1": "Second", "Category2": "A", "Category3": "2"}, {"Health_Camp_ID": 6541, "Camp_Start_Date": "03-Dec-05", "Camp_End_Date": "30-Jan-06", "Category1": "Third", "Category2": "G", "Category3": "2"}, {"Health_Camp_ID": 6528, "Camp_Start_Date": "10-Feb-06", "Camp_End_Date": "25-Apr-06", "Category1": "Third", "Category2": "G", "Category3": "2"}, {"Health_Camp_ID": 6529, "Camp_Start_Date": "30-Mar-06", "Camp_End_Date": "03-Apr-06", "Category1": "Second", "Category2": "A", "Category3": "2"}, {"Health_Camp_ID": 6547, "Camp_Start_Date": "02-Apr-06", "Camp_End_Date": "07-Apr-06", "Category1": "First", "Category2": "C", "Category3": "2"}, {"Health_Camp_ID": 6582, "Camp_Start_Date": "06-Apr-06", "Camp_End_Date": "07-Nov-07", "Category1": "First", "Category2": "F", "Category3": "2"}, {"Health_Camp_ID": 6525, "Camp_Start_Date": "08-Apr-06", "Camp_End_Date": "17-Apr-06", "Category1": "First", "Category2": "C", "Category3": "2"}, {"Health_Camp_ID": 6566, "Camp_Start_Date": "18-Apr-06", "Camp_End_Date": "25-Apr-06", "Category1": "First", "Category2": "E", "Category3": "2"}, {"Health_Camp_ID": 6574, "Camp_Start_Date": "12-May-06", "Camp_End_Date": "18-Aug-06", "Category1": "Third", "Category2": "G", "Category3": "2"}, {"Health_Camp_ID": 6548, "Camp_Start_Date": "13-Jun-06", "Camp_End_Date": "18-Aug-06", "Category1": "Third", "Category2": "G", "Category3": "2"}, {"Health_Camp_ID": 6572, "Camp_Start_Date": "05-Jul-06", "Camp_End_Date": "10-Jul-06", "Category1": "First", "Category2": "C", "Category3": "2"}, {"Health_Camp_ID": 6583, "Camp_Start_Date": "02-Aug-06", "Camp_End_Date": "05-Aug-06", "Category1": "Second", "Category2": "A", "Category3": "2"}, {"Health_Camp_ID": 6584, "Camp_Start_Date": "04-Aug-06", "Camp_End_Date": "09-Aug-06", "Category1": "Second", "Category2": "A", "Category3": "2"}, {"Health_Camp_ID": 6568, "Camp_Start_Date": "17-Aug-06", "Camp_End_Date": "13-Sep-06", "Category1": "First", "Category2": "E", "Category3": "2"}, {"Health_Camp_ID": 6576, "Camp_Start_Date": "19-Aug-06", "Camp_End_Date": "07-Nov-07", "Category1": "Third", "Category2": "G", "Category3": "2"}, {"Health_Camp_ID": 6533, "Camp_Start_Date": "20-Sep-06", "Camp_End_Date": "23-Sep-06", "Category1": "First", "Category2": "E", "Category3": "2"}, {"Health_Camp_ID": 6545, "Camp_Start_Date": "22-Sep-06", "Camp_End_Date": "27-Sep-06", "Category1": "First", "Category2": "C", "Category3": "2"}, {"Health_Camp_ID": 6579, "Camp_Start_Date": "22-Sep-06", "Camp_End_Date": "27-Sep-06", "Category1": "Second", "Category2": "A", "Category3": "2"}, {"Health_Camp_ID": 6550, "Camp_Start_Date": "12-Oct-06", "Camp_End_Date": "18-Dec-06", "Category1": "Third", "Category2": "G", "Category3": "2"}, {"Health_Camp_ID": 6573, "Camp_Start_Date": "09-Nov-06", "Camp_End_Date": "16-Mar-07", "Category1": "Third", "Category2": "G", "Category3": "2"}, {"Health_Camp_ID": 6556, "Camp_Start_Date": "09-Nov-06", "Camp_End_Date": "15-Dec-06", "Category1": "First", "Category2": "E", "Category3": "2"}, {"Health_Camp_ID": 6551, "Camp_Start_Date": "13-Nov-06", "Camp_End_Date": "18-Nov-06", "Category1": "Second", "Category2": "D", "Category3": "2"}, {"Health_Camp_ID": 6559, "Camp_Start_Date": "11-Dec-06", "Camp_End_Date": "12-Mar-07", "Category1": "First", "Category2": "F", "Category3": "2"}, {"Health_Camp_ID": 6567, "Camp_Start_Date": "30-Jan-07", "Camp_End_Date": "04-Feb-07", "Category1": "Second", "Category2": "D", "Category3": "2"}, {"Health_Camp_ID": 6577, "Camp_Start_Date": "30-Jan-07", "Camp_End_Date": "08-Mar-07", "Category1": "Third", "Category2": "G", "Category3": "2"}]